{"inkVersion":21,"root":[["^What do you do?","\n",{"->":"My_WorkChoices"},["done",{"#f":5,"#n":"g-0"}],null],"done",{"My_WorkChoices":[["ev","str","^I work at a public school.","/str","/ev",{"*":".^.c-0","flg":20},"ev","str","^I’m a consultant.","/str","/ev",{"*":".^.c-1","flg":20},"ev","str","^Your mom!","/str","/ev",{"*":".^.c-2","flg":20},{"c-0":["^ ",{"->":"increase_stability"},"\n",{"#f":5}],"c-1":["^ ",{"->":"decrease_stability"},"\n",{"#f":5}],"c-2":["^ ",{"->":"major_decrease_stability"},"\n",{"#f":5}]}],{"#f":1}],"increase_stability":["ev",{"VAR?":"stability"},1,"+",{"VAR=":"stability","re":true},"/ev","^Great!","\n",{"->":"Morning"},{"#f":1}],"decrease_stability":["ev",{"VAR?":"stability"},1,"-",{"VAR=":"stability","re":true},"/ev","^Nope! Stability Decrease.","\n",{"->":"Morning"},{"#f":1}],"major_decrease_stability":["ev",{"VAR?":"stability"},2,"-",{"VAR=":"stability","re":true},"/ev","^Nuh uh! BIGGER Stability Decrease.","\n",{"->":"Morning"},{"#f":1}],"Morning":[["^Good morning! How are you?","\n","ev","str","^Good! How are you?","/str","/ev",{"*":".^.c-0","flg":20},"ev","str","^We’re doing well!","/str","/ev",{"*":".^.c-1","flg":20},"ev","str","^Stranger Danger!","/str","/ev",{"*":".^.c-2","flg":20},{"c-0":["^ ",{"->":"morn_increase_stability"},"\n",{"#f":5}],"c-1":["^ ",{"->":"morn_decrease_stability"},"\n",{"#f":5}],"c-2":["^ ",{"->":"morn_major_decrease_stability"},"\n",{"#f":5}]}],{"#f":1}],"morn_increase_stability":["ev",{"VAR?":"stability"},1,"+",{"VAR=":"stability","re":true},"/ev","^Great!","\n",{"->":"Marriage"},{"#f":1}],"morn_decrease_stability":["ev",{"VAR?":"stability"},1,"-",{"VAR=":"stability","re":true},"/ev","^Nope! Stability Decrease.","\n",{"->":"Marriage"},{"#f":1}],"morn_major_decrease_stability":["ev",{"VAR?":"stability"},2,"-",{"VAR=":"stability","re":true},"/ev","^Nuh uh! BIGGER Stability Decrease.","\n",{"->":"Marriage"},{"#f":1}],"Marriage":[["^(exasperated) Guess what?! I'm getting married!","\n","ev","str","^Congratulations","/str","/ev",{"*":".^.c-0","flg":20},"ev","str","^So am I! Congratulations","/str","/ev",{"*":".^.c-1","flg":20},"ev","str","^My fiancee's hotter than you","/str","/ev",{"*":".^.c-2","flg":20},{"c-0":["^ ",{"->":"mar_increase_stability"},"\n",{"#f":5}],"c-1":["^ ",{"->":"mar_decrease_stability"},"\n",{"#f":5}],"c-2":["^ ",{"->":"mar_major_decrease_stability"},"\n",{"#f":5}]}],{"#f":1}],"mar_increase_stability":["ev",{"VAR?":"stability"},1,"+",{"VAR=":"stability","re":true},"/ev","^Great!","\n",{"->":"Weather"},{"#f":1}],"mar_decrease_stability":["ev",{"VAR?":"stability"},1,"-",{"VAR=":"stability","re":true},"/ev","^Nope! Stability Decrease.","\n",{"->":"Weather"},{"#f":1}],"mar_major_decrease_stability":["ev",{"VAR?":"stability"},2,"-",{"VAR=":"stability","re":true},"/ev","^Nuh uh! BIGGER Stability Decrease.","\n",{"->":"Weather"},{"#f":1}],"Weather":[["^Wonderful weather we’re having, huh? Pretty hot, though…","\n","ev","str","^Yeah, well, you know, it’s not the heat, it’s the humidity!","/str","/ev",{"*":".^.c-0","flg":20},"ev","str","^It’s not that bad, really.","/str","/ev",{"*":".^.c-1","flg":20},"ev","str","^I’m dying in this heat!","/str","/ev",{"*":".^.c-2","flg":20},{"c-0":["^ ",{"->":"weat_increase_stability"},"\n",{"#f":5}],"c-1":["^ ",{"->":"weat_decrease_stability"},"\n",{"#f":5}],"c-2":["^ ",{"->":"weat_major_decrease_stability"},"\n",{"#f":5}]}],{"#f":1}],"weat_increase_stability":["ev",{"VAR?":"stability"},1,"+",{"VAR=":"stability","re":true},"/ev","^Great!","\n",{"->":"Weather"},{"#f":1}],"weat_decrease_stability":["ev",{"VAR?":"stability"},1,"-",{"VAR=":"stability","re":true},"/ev","^Nope! Stability Decrease.","\n",{"->":"Weather"},{"#f":1}],"weat_major_decrease_stability":["ev",{"VAR?":"stability"},2,"-",{"VAR=":"stability","re":true},"/ev","^Nuh uh! BIGGER Stability Decrease.","\n",{"->":"Weather"},{"->":"Kids"},{"#f":1}],"Kids":[["^(exasperated) Kids, am I right?","\n","ev","str","^They definitely are a handful.","/str","/ev",{"*":".^.c-0","flg":20},"ev","str","^I know! I’m a dad, too.","/str","/ev",{"*":".^.c-1","flg":20},"ev","str","^Maybe you should be less of a hardass.","/str","/ev",{"*":".^.c-2","flg":20},{"c-0":["^ ",{"->":"kids_increase_stability"},"\n",{"#f":5}],"c-1":["^ ",{"->":"kids_decrease_stability"},"\n",{"#f":5}],"c-2":["^ ",{"->":"kids_major_decrease_stability"},"\n",{"#f":5}]}],{"#f":1}],"kids_increase_stability":["ev",{"VAR?":"stability"},1,"+",{"VAR=":"stability","re":true},"/ev","^Great!","\n",{"->":"Kids"},{"#f":1}],"kids_decrease_stability":["ev",{"VAR?":"stability"},1,"-",{"VAR=":"stability","re":true},"/ev","^Nope! Stability Decrease.","\n",{"->":"Kids"},{"#f":1}],"kids_major_decrease_stability":["ev",{"VAR?":"stability"},2,"-",{"VAR=":"stability","re":true},"/ev","^Nuh uh! BIGGER Stability Decrease.","\n",{"->":"Weekend"},{"#f":1}],"Weekend":[["^Any plans for the weekend?","\n","ev","str","^Just gonna relax and watch a movie.","/str","/ev",{"*":".^.c-0","flg":20},"ev","str","^Gonna mow my lawn and fix the garage.","/str","/ev",{"*":".^.c-1","flg":20},"ev","str","^I’ve got a LOT of homework to finish up.","/str","/ev",{"*":".^.c-2","flg":20},{"c-0":["^ ",{"->":"wk_increase_stability"},"\n",{"#f":5}],"c-1":["^ ",{"->":"wk_decrease_stability"},"\n",{"#f":5}],"c-2":["^ ",{"->":"wk_major_decrease_stability"},"\n",{"#f":5}]}],{"#f":1}],"wk_increase_stability":["ev",{"VAR?":"stability"},1,"+",{"VAR=":"stability","re":true},"/ev","^Great!","\n",{"->":"News"},{"#f":1}],"wk_decrease_stability":["ev",{"VAR?":"stability"},1,"-",{"VAR=":"stability","re":true},"/ev","^Nope! Stability Decrease.","\n",{"->":"News"},{"#f":1}],"wk_major_decrease_stability":["ev",{"VAR?":"stability"},2,"-",{"VAR=":"stability","re":true},"/ev","^Nuh uh! BIGGER Stability Decrease.","\n",{"->":"Kids"},{"#f":1}],"News":[["^Did you see that thing on the news","\n","ev","str","^Yes, I’ve heard of something big happening this weekend.","/str","/ev",{"*":".^.c-0","flg":20},"ev","str","^No.","/str","/ev",{"*":".^.c-1","flg":20},"ev","str","^Why would I watch the news?","/str","/ev",{"*":".^.c-2","flg":20},{"c-0":["^ ",{"->":"new_increase_stability"},"\n",{"#f":5}],"c-1":["^ ",{"->":"decrease_stability"},"\n",{"#f":5}],"c-2":["^ ",{"->":"major_decrease_stability"},"\n",{"#f":5}]}],{"#f":1}],"new_increase_stability":["ev",{"VAR?":"stability"},1,"+",{"VAR=":"stability","re":true},"/ev","^Great!","\n",{"->":"Stock"},{"#f":1}],"new_decrease_stability":["ev",{"VAR?":"stability"},1,"-",{"VAR=":"stability","re":true},"/ev","^Nope! Stability Decrease.","\n",{"->":"Stock"},{"#f":1}],"new_major_decrease_stability":["ev",{"VAR?":"stability"},2,"-",{"VAR=":"stability","re":true},"/ev","^Nuh uh! BIGGER Stability Decrease.","\n",{"->":"Stock"},{"#f":1}],"Stock":[["^What do you think about the stock market?","\n","ev","str","^I’ve heard it’s always unpredictable, best to keep a diversified portfolio.","/str","/ev",{"*":".^.c-0","flg":20},"ev","str","^Oh, I play it safe with my piggy bank.","/str","/ev",{"*":".^.c-1","flg":20},"ev","str","^Like… at the Costco?","/str","/ev",{"*":".^.c-2","flg":20},{"c-0":["^ ",{"->":"increase_stability"},"\n",{"#f":5}],"c-1":["^ ",{"->":"decrease_stability"},"\n",{"#f":5}],"c-2":["^ ",{"->":"major_decrease_stability"},"\n",{"->":"Age"},{"#f":5}]}],{"#f":1}],"Age":[["^How old are you?","\n","ev","str","^The years of life earned is totaled to 24 years.","/str","/ev",{"*":".^.c-0","flg":20},"ev","str","^I am 18 years old, an adult.","/str","/ev",{"*":".^.c-1","flg":20},"ev","str","^Not nearly as old as you but old enough.","/str","/ev",{"*":".^.c-2","flg":20},{"c-0":["^ ",{"->":"increase_stability"},"\n",{"#f":5}],"c-1":["^ ",{"->":"decrease_stability"},"\n",{"#f":5}],"c-2":["^ ",{"->":"major_decrease_stability"},"\n","end",{"#f":5}]}],{"#f":1}],"global decl":["ev",10,{"VAR=":"stability"},"/ev","end",null],"#f":1}],"listDefs":{}}